{
  "dataList": [
    {
      "id": 1001,
      "name": "<line-height=120%>The Forgotten\u200B</line-height>"
    },
    {
      "id": 1002,
      "name": "<line-height=120%>The Outcast\u200B</line-height>"
    },
    {
      "id": 1003,
      "name": "<line-height=120%>Flat-broke Gamblers\u200B</line-height>"
    },
    {
      "id": 1004,
      "name": "<line-height=120%>Automated Factory\u200B</line-height>"
    },
    {
      "id": 1005,
      "name": "<line-height=120%>The Unloving\u200B</line-height>"
    },
    {
      "id": 1006,
      "name": "<line-height=120%>Nagel und Hammer\u200B</line-height>"
    },
    {
      "id": 1007,
      "name": "<line-height=120%>Faith & Erosion\u200B</line-height>"
    },
    {
      "id": 1008,
      "name": "<line-height=120%>The Unconfronting\u200B</line-height>"
    },
    {
      "id": 1009,
      "name": "<line-height=120%>Nest, Workshop, and Technology\u200B</line-height>"
    },
    {
      "id": 1010,
      "name": "<line-height=120%>Falling Flowers\u200B</line-height>"
    },
    {
      "id": 1011,
      "name": "<line-height=120%>Tearful Things\u200B</line-height>"
    },
    {
      "id": 1012,
      "name": "<line-height=120%>The Unchanging\u200B</line-height>"
    },
    {
      "id": 1013,
      "name": "<line-height=120%>Lake World\u200B</line-height>"
    },
    {
      "id": 1014,
      "name": "<line-height=120%>Crawling Abyss\u200B</line-height>"
    },
    {
      "id": 1015,
      "name": "<line-height=120%>The Evil Defining\u200B</line-height>"
    },
    {
      "id": 1016,
      "name": "<line-height=120%>Dregs of the Manor\u200B</line-height>"
    },
    {
      "id": 1017,
      "name": "<line-height=120%>A Certain World\u200B</line-height>"
    },
    {
      "id": 1101,
      "name": "<line-height=120%>Hell's Chicken\u200B</line-height>"
    },
    {
      "id": 1102,
      "name": "<line-height=120%>S.E.A.\u200B</line-height>"
    },
    {
      "id": 1103,
      "name": "<line-height=120%>Miracle in District 20\u200B</line-height>"
    },
    {
      "id": 1104,
      "name": "<line-height=120%>Yield My Flesh to Claim Their Bones\u200B</line-height>"
    },
    {
      "id": 1201,
      "name": "<line-height=120%>Slicers & Dicers\u200B</line-height>"
    },
    {
      "id": 1202,
      "name": "<line-height=120%>To be Cleaved\u200B</line-height>"
    },
    {
      "id": 1203,
      "name": "<line-height=120%>Piercers & Penetrators\u200B</line-height>"
    },
    {
      "id": 1204,
      "name": "<line-height=120%>To be Pierced\u200B</line-height>"
    },
    {
      "id": 1205,
      "name": "<line-height=120%>Crushers & Breakers\u200B</line-height>"
    },
    {
      "id": 1206,
      "name": "<line-height=120%>To be Crushed\u200B</line-height>"
    },
    {
      "id": 1301,
      "name": "<line-height=120%>Repressed Wrath\u200B</line-height>"
    },
    {
      "id": 1302,
      "name": "<line-height=120%>Unbound Wrath\u200B</line-height>"
    },
    {
      "id": 1303,
      "name": "<line-height=120%>Emotional Repression\u200B</line-height>"
    },
    {
      "id": 1304,
      "name": "<line-height=120%>Addicting Lust\u200B</line-height>"
    },
    {
      "id": 1305,
      "name": "<line-height=120%>Tangling Lust\u200B</line-height>"
    },
    {
      "id": 1306,
      "name": "<line-height=120%>Emotional Seduction\u200B</line-height>"
    },
    {
      "id": 1307,
      "name": "<line-height=120%>Treadwheel Sloth\u200B</line-height>"
    },
    {
      "id": 1308,
      "name": "<line-height=120%>Inert Sloth\u200B</line-height>"
    },
    {
      "id": 1309,
      "name": "<line-height=120%>Emotional Indolence\u200B</line-height>"
    },
    {
      "id": 1310,
      "name": "<line-height=120%>Devoured Gluttony\u200B</line-height>"
    },
    {
      "id": 1311,
      "name": "<line-height=120%>Excessive Gluttony\u200B</line-height>"
    },
    {
      "id": 1312,
      "name": "<line-height=120%>Emotional Craving\u200B</line-height>"
    },
    {
      "id": 1313,
      "name": "<line-height=120%>Degraded Gloom\u200B</line-height>"
    },
    {
      "id": 1314,
      "name": "<line-height=120%>Sunk Gloom\u200B</line-height>"
    },
    {
      "id": 1315,
      "name": "<line-height=120%>Emotional Flood\u200B</line-height>"
    },
    {
      "id": 1316,
      "name": "<line-height=120%>Vain Pride\u200B</line-height>"
    },
    {
      "id": 1317,
      "name": "<line-height=120%>Tyrannical Pride\u200B</line-height>"
    },
    {
      "id": 1318,
      "name": "<line-height=120%>Emotional Subservience\u200B</line-height>"
    },
    {
      "id": 1319,
      "name": "<line-height=120%>Insignificant Envy\u200B</line-height>"
    },
    {
      "id": 1320,
      "name": "<line-height=120%>Pitiful Envy\u200B</line-height>"
    },
    {
      "id": 1321,
      "name": "<line-height=120%>Emotional Judgment\u200B</line-height>"
    },
    {
      "id": 1401,
      "name": "<line-height=120%>Burning Haze\u200B</line-height>"
    },
    {
      "id": 1402,
      "name": "<line-height=120%>Season of the Flame\u200B</line-height>"
    },
    {
      "id": 1403,
      "name": "<line-height=120%>Trickled Sanguine Blood\u200B</line-height>"
    },
    {
      "id": 1404,
      "name": "<line-height=120%>Mountain of Corpses, Sea of Blood\u200B</line-height>"
    },
    {
      "id": 1405,
      "name": "<line-height=120%>Dizzying Waves\u200B</line-height>"
    },
    {
      "id": 1406,
      "name": "<line-height=120%>Abnormal Seismic Zone\u200B</line-height>"
    },
    {
      "id": 1407,
      "name": "<line-height=120%>Crushing External Force\u200B</line-height>"
    },
    {
      "id": 1408,
      "name": "<line-height=120%>Unrelenting Might\u200B</line-height>"
    },
    {
      "id": 1409,
      "name": "<line-height=120%>Sinking Pang\u200B</line-height>"
    },
    {
      "id": 1410,
      "name": "<line-height=120%>Sinking Deluge\u200B</line-height>"
    },
    {
      "id": 1411,
      "name": "<line-height=120%>Deep Sigh\u200B</line-height>"
    },
    {
      "id": 1412,
      "name": "<line-height=120%>Poised Breathing\u200B</line-height>"
    },
    {
      "id": 1413,
      "name": "<line-height=120%>Rising Power Supply\u200B</line-height>"
    },
    {
      "id": 1414,
      "name": "<line-height=120%>Thunder and Lightning\u200B</line-height>"
    },
    {
      "id": 1105,
      "name": "<line-height=120%>Timekilling Time\u200B</line-height>"
    },
    {
      "id": 1106,
      "name": "<line-height=120%>Murder on the WARP Express\u200B</line-height>"
    },
    {
      "id": 1107,
      "name": "<line-height=120%>The Noon of Violet\u200B</line-height>"
    },
    {
      "id": 1018,
      "name": "<line-height=120%>The Heartbreaking\u200B</line-height>"
    },
    {
      "id": 1019,
      "name": "<line-height=120%>La Manchaland Re-opening\u200B</line-height>"
    },
    {
      "id": 1020,
      "name": "<line-height=120%>The Infinite Procession\u200B</line-height>"
    },
    {
      "id": 1108,
      "name": "<line-height=120%>Line 1\u200B</line-height>"
    },
    {
      "id": 1109,
      "name": "<line-height=120%>Line 2\u200B</line-height>"
    },
    {
      "id": 1110,
      "name": "<line-height=120%>Line 3\u200B</line-height>"
    },
    {
      "id": 1111,
      "name": "<line-height=120%>Line 4 - Section #3\u200B</line-height>"
    },
    {
      "id": 1112,
      "name": "<line-height=120%>Line 4 - Section #4\u200B</line-height>"
    },
    {
      "id": 1113,
      "name": "<line-height=120%>Miracle in District 20 BokGak\u200B</line-height>"
    },
    {
      "id": 1114,
      "name": "<line-height=120%>Full-Stopped by a Bullet\u200B</line-height>"
    },
    {
      "id": 1115,
      "name": "<line-height=120%>LCB Regular Check-up\u200B</line-height>"
    },
    {
      "id": 1116,
      "name": "<line-height=120%>Yield My Flesh to Claim Their Bones BokGak\u200B</line-height>"
    },
    {
      "id": 1117,
      "name": "<line-height=120%>Nocturnal Sweeping\u200B</line-height>"
    }
  ]
}