{
  "dataList": [
    {
      "id": 863001,
      "name": "<line-height=120%>Melee Combat\u200B</line-height>",
      "desc": "หากยูนิทนี้'s Speed is faster than the target's, ทำ +10% more ความเสียหาย for every Speed difference (สูงสุด 30%)\nหากยูนิทนี้'s Speed is slower than the target's ทำ -10% less ความเสียหาย for every Speed difference (สูงสุด 30%)"
    },
    {
      "id": 863002,
      "name": "<line-height=120%>Charge Forth\u200B</line-height>",
      "desc": "Raise Min & สูงสุด Speed values by 1 for every 5 [Breath] on self (สูงสุด 4)"
    },
    {
      "id": 863003,
      "name": "<line-height=120%>Summon Targets\u200B</line-height>",
      "desc": "At 75%- HP, ได้รับ a new pattern\nเมื่อ gaining a new pattern, summon G Corp. Head Manager และ Downcast Veteran; then, มอบ Stigmatized on theเป้าหมายwith the least current HP\n- Change Min & สูงสุด Speed values on self to 1.\n- ได้รับ 300 Shield HP."
    },
    {
      "id": 863004,
      "name": "<line-height=120%>Designate Target\u200B</line-height>",
      "desc": "เมื่อ using Designatedเป้าหมายFire orเป้าหมายReadjustment Fire: among targets with the slowest Speed, มอบ [FellBulletMark] againstเป้าหมายwith the least current HP"
    },
    {
      "id": 863201,
      "name": "<line-height=120%>Oxygen Supply\u200B</line-height>",
      "desc": "At the first Turn Start of the turn Sleeping Bag of a Bygone Day appeared, it gains 10 [Breath] Potency และ +10 [Breath] Count\n\nTurn End: at less than 10 [Breath] Potency or [Breath] Count, consume HP จาก the Head Part equal to 2% of the Core's HP สูงสุด to ได้รับ 5 [Breath] และ +5 [Breath] Count (cannot be Part broken or defeated due to this effect)"
    },
    {
      "id": 863202,
      "name": "<line-height=120%>Deep Breath\u200B</line-height>",
      "desc": "Multiply Critical Chance จาก [Breath] effects by x 1.5\n\nOn Crit:\n- At 15+ [Breath] Potency, consume up to ([Breath] Potency on self / 5) [Breath] Potency to ทำ +([Breath] Potency consumed x 4)% more ความเสียหาย on Crit\n- At 15+ [Breath] Count, consume up t ([Breath] Count on self / 5) [Breath] Count to ทำ +([Breath] Count consumed x 8)% more ความเสียหาย on Crit"
    },
    {
      "id": 863203,
      "name": "<line-height=120%>Oxygen-saturated\u200B</line-height>",
      "desc": "In the turnยูนิทนี้ uses 'That's... Mine!', fix its Speed to 1. เมื่อเริ่มเทิร์น, apply 6 [Breath] Potency และ +6 [Breath] Count to all units present on the Stage.\n\nAt the end of the same turn, consume any excess [Breath] Potency และ [Breath] Count past 5 Potency และ 5 Count; then, at the ในเทิร์นหน้า Start, apply the same amount of [Breath] Potency และ [Breath] Count consumed to the Head Part"
    },
    {
      "id": 863204,
      "name": "<line-height=120%>Shattered Ribcage\u200B</line-height>",
      "desc": "เมื่อ the Body Part is broken, ลบ the Body Part ในเทิร์นหน้า และ replace it with a Person Part"
    },
    {
      "id": 863205,
      "name": "<line-height=120%>Ribcage Regeneration\u200B</line-height>",
      "desc": "At Combat End, halve the [Breath] Potency และ [Breath] Count on the Person Part\nในเทิร์นหน้า, the Person Part disappears และ is replaced by Body Part"
    },
    {
      "id": 863206,
      "name": "<line-height=120%>Excruciating Suffering\u200B</line-height>",
      "desc": "Every timeยูนิทนี้ เสีย a Clash และ takes a hit, เสีย 1 [Breath] Potency\n\nEvery timeยูนิทนี้ is hit by an Unopposed Attack, เสีย 1 [Breath] Count\n\nยูนิทนี้'s [Breath] Potency และ [Breath] Count, regardless of whether an attack hit Critically or whether its Passive activated, ไม่ลดต่ำไปกว่า 5"
    },
    {
      "id": 863207,
      "name": "<line-height=120%>Anguished Screaming\u200B</line-height>",
      "desc": "At 40% or less Core HP, use 'Share the Pain' ในเทิร์นหน้า"
    },
    {
      "id": 863208,
      "name": "<line-height=120%>หลังจากEffect\u200B</line-height>",
      "desc": "เมื่อ the Person dies, both the Body และ the Head Parts ได้รับ +0.2 Resistance to Slash, Pierce, และ Blunt until ในเทิร์นหน้า (once per Encounter)"
    },
    {
      "id": 863301,
      "name": "<line-height=120%>Indulgent Petals\u200B</line-height>",
      "desc": "Turn End: at 20+ [BloodDinner], consume up to 50 [BloodDinner] และ heal the Core และ the Head Parts equal to [BloodDinner] consumed\n- Does not activate if the Head Part is either Staggered or Destroyed"
    },
    {
      "id": 863302,
      "name": "<line-height=120%>A Drop of Nourishment\u200B</line-height>",
      "desc": "หลังจากAttack, heal the Core และ the Part equal to the amount of ความเสียหายยูนิทนี้'s Attack Skill dealt\n- Does not activate if the Head Part is either Staggered or Destroyed"
    },
    {
      "id": 863303,
      "name": "<line-height=120%>Yearning\u200B</line-height>",
      "desc": "Turn End: ifยูนิทนี้ healed HP, ได้รับ 1 [AttackUp] และ 1 [DefenseDown] ในเทิร์นหน้า for every 10 HP healed (สูงสุด 10)"
    },
    {
      "id": 863304,
      "name": "<line-height=120%>Bloodthirsty Stench\u200B</line-height>",
      "desc": "เมื่อมี 100+ [BloodDinner], use a special Skill\nTurn End: เมื่อมี 500+ [BloodDinner_Accumulation] byยูนิทนี้, or ifยูนิทนี้ is เมื่อมี HP น้อยกว่า 60%, ได้รับ a new pattern"
    },
    {
      "id": 863305,
      "name": "<line-height=120%>Refracted Sin\u200B</line-height>",
      "desc": "[Combustion], [Laceration], [Vibration], [Burst], และ [Sinking] Potency only stacks up to 50 (including the Unique variations of above Keywords)"
    },
    {
      "id": 863306,
      "name": "<line-height=120%>Sharp Thorn\u200B</line-height>",
      "desc": "หากยูนิทนี้'s Body Part takes ความเสียหาย จาก an enemy Skill, มอบ +1 [Laceration] Count on the attacker (once per turn per Identity)"
    },
    {
      "id": 863307,
      "name": "<line-height=120%>Endless Thirst\u200B</line-height>",
      "desc": "Turn Start: ได้รับ 1 [DefenseDown] for every 100 [BloodDinner_Accumulation] byยูนิทนี้ (สูงสุด 10)\nTurn Start: ได้รับ 1 [TakeHpHealIncrease] for every 200 [BloodDinner_Accumulation] byยูนิทนี้ (สูงสุด 5)"
    },
    {
      "id": 863308,
      "name": "<line-height=120%>Endless Yearning\u200B</line-height>",
      "desc": "Triggers a Choice Event every 'multiple of 3' turns."
    },
    {
      "id": 863309,
      "name": "<line-height=120%>Increased Refraction Rate\u200B</line-height>",
      "desc": "หาก 9 turns have passed sinceยูนิทนี้ appeared on the field, starting ในเทิร์นหน้า, ได้รับ 1 [AttackUp] every turn past the 10th turn (สูงสุด 10)"
    },
    {
      "id": 863101,
      "name": "<line-height=120%>Designated Execution\u200B</line-height>",
      "desc": "เมื่อ killed by Der Fluchschütze, apply 1 [Agility], 1 [Enhancement], และ 2 [AttackDmgUp] ในเทิร์นหน้า to Der Fluchschütze"
    },
    {
      "id": 863102,
      "name": "<line-height=120%>First Strike Wins\u200B</line-height>",
      "desc": "เมื่อ killed by a Sinner, give 3 E.G.O resources in the affinity of the Skill that killedยูนิทนี้"
    },
    {
      "id": 863103,
      "name": "<line-height=120%>Not Me\u200B</line-height>",
      "desc": "หากยูนิทนี้ doesn't have Stigmatized at Combat Start, ได้รับ 300 Shield."
    }
  ]
}