{
  "dataList": [
    {
      "id": "OnSucceedAttack",
      "name": "[เมื่อโจมตี]"
    },
    {
      "id": "WhenUse",
      "name": "[เมื่อใช้]"
    },
    {
      "id": "WinDuel",
      "name": "[ชนะการปะทะ]"
    },
    {
      "id": "BeforeAttack",
      "name": "[ก่อนโจมตี]"
    },
    {
      "id": "Wide",
      "name": "[โจมตีวงกว้าง]"
    },
    {
      "id": "nxPostLine",
      "name": "[{n} ข้างหน้า]"
    },
    {
      "id": "nxCenterLine",
      "name": "[{n} ตรงกลาง]"
    },
    {
      "id": "nxBackLine",
      "name": "[{n} ข้างหลัง]"
    },
    {
      "id": "CantIdentify",
      "name": "[คาดเดาไม่ได้]"
    },
    {
      "id": "CRIMSON",
      "name": "<line-height=120%>Crimson\u200B</line-height>"
    },
    {
      "id": "SCARLET",
      "name": "<line-height=120%>Scarlet\u200B</line-height>"
    },
    {
      "id": "AMBER",
      "name": "<line-height=120%>Amber\u200B</line-height>"
    },
    {
      "id": "SHAMROCK",
      "name": "<line-height=120%>Shamrock\u200B</line-height>"
    },
    {
      "id": "AZURE",
      "name": "<line-height=120%>Azure\u200B</line-height>"
    },
    {
      "id": "INDIGO",
      "name": "<line-height=120%>Indigo\u200B</line-height>"
    },
    {
      "id": "VIOLET",
      "name": "<line-height=120%>Violet\u200B</line-height>"
    },
    {
      "id": "WHITE",
      "name": "<line-height=120%>White\u200B</line-height>"
    },
    {
      "id": "BLACK",
      "name": "<line-height=120%>Black\u200B</line-height>"
    },
    {
      "id": "EndSkill",
      "name": "[หลังโจมตี]"
    },
    {
      "id": "StartBattle",
      "name": "[เริ่มการต่อสู้]"
    },
    {
      "id": "DefeatDuel",
      "name": "[แพ้การปะทะ]"
    },
    {
      "id": "OnSucceedAttackHead",
      "name": "[ทอยหัว]"
    },
    {
      "id": "OnSucceedAttackTail",
      "name": "[ทอยก้อย]"
    },
    {
      "id": "OnSucceedEvade",
      "name": "[เมื่อหลบ]"
    },
    {
      "id": "AlwaysUse",
      "name": "[ใช้งานเสมอ]"
    },
    {
      "id": "CantDuel",
      "name": "[ไม่สามารถปะทะได้]"
    },
    {
      "id": "EnemyKill",
      "name": "[เมื่อฆ่า]"
    },
    {
      "id": "EnemyKillFail",
      "name": "[เมื่อฆ่าไม่ได้]"
    },
    {
      "id": "ReUse",
      "name": "[เมื่อใช้อีกครั้ง]"
    },
    {
      "id": "ReUseOnSucceedAttackHead",
      "name": "[ใช้อีกครั้ง - ทอยหัว]"
    },
    {
      "id": "CriticalOnSucceedAttack",
      "name": "[เมื่อโจมตีคริติคอล]"
    },
    {
      "id": "StartDuel",
      "name": "[เมื่อเริ่มการปะทะ]"
    },
    {
      "id": "EndBattle",
      "name": "[จบเทิร์น]"
    },
    {
      "id": "OnDefeatEvade",
      "name": "[เมื่อหลบพลาด]"
    },
    {
      "id": "EndSkillHead",
      "name": "[เมื่อการโจมตีทอยหัวจบลง]"
    },
    {
      "id": "EndSkillTail",
      "name": "[เมื่อการโจมตีทอยก้อยจบลง]"
    },
    {
      "id": "WinDuelAttackHead",
      "name": "[ทอยหัวเมื่อชนะการปะทะ]"
    },
    {
      "id": "WinDuelAttack",
      "name": "[เมื่อโจมตีหลังจากชนะการปะทะ]"
    },
    {
      "id": "CriticalActivated",
      "name": "[เมื่อติดคริติคอล]"
    },
    {
      "id": "CriticalEndSkill",
      "name": "[เมื่อการโจมตีคริติคอลจบลง]"
    },
    {
      "id": "CantChangeTarget",
      "name": "[เป้าหมายกำหนดไว้]"
    },
    {
      "id": "TurnStartBattle",
      "name": "[เมื่อเริ่มเทิร์น]"
    },
    {
      "id": "EndSkillAll",
      "name": "[เมื่อสกิลจบลง]"
    },
    {
      "id": "WhenUse_Force",
      "name": "<color=#26cfff>[เมื่อใช้]</color>"
    },
    {
      "id": "StartBattle_Force",
      "name": "<color=#93f13e>[เมื่อเริ่มการต่อสู้]</color>"
    },
    {
      "id": "TargetKill",
      "name": "[เมื่อฆ่าเป้าหมายได้]"
    },
    {
      "id": "CriticalTargetKill",
      "name": "[เมื่อการโจมตีคริติคอลฆ่าได้]"
    },
    {
      "id": "BeforeUse",
      "name": "[ก่อนใช้]"
    },
    {
      "id": "DuelCounter",
      "name": "[การโจมตีสวนแบบปะทะได้]"
    },
    {
      "id": "CantBreak",
      "name": "[เหรียญที่ทำลายไม่ได้]"
    },
    {
      "id": "DuelGuard",
      "name": "[การป้องกันแบบปะทะได้]"
    },
    {
      "id": "WhenUseEvade",
      "name": "[เมื่อใช้หลบ]"
    },
    {
      "id": "EndCoin",
      "name": "[หลังจากเหรียญโจมตีนี้]"
    },
    {
      "id": "CriticalEnemyTargetKillFail",
      "name": "[เมื่อการโจมตีคริติคอลฆ่าศัตรูไม่ได้]"
    },
    {
      "id": "CriticalEnemyTargetKill",
      "name": "[เมื่อการโจมตีคริติคอลแล้วฆ่าศัตรูได้]"
    },
    {
      "id": "DefeatDuelAttack",
      "name": "[เมื่อโจมตีหลังจากแพ้การปะทะ]"
    },
    {
      "id": "TargetKillFail",
      "name": "[เมื่อฆ่าเป้าหมายพลาด]"
    },
    {
      "id": "AllyKill",
      "name": "[เมื่อฆ่าพันธมิตร]"
    },
    {
      "id": "AllyKillFail",
      "name": "[เมื่อฆ่าพันธมิตรพลาด]"
    },
    {
      "id": "TabExplain",
      "name": ""
    },
    {
      "id": "UnBrokenCoinOnSucceedAttack",
      "name": "[เมื่อโจมตีโดยเหรียญไม่แตกร้าว]"
    },
    {
      "id": "BeforeHit",
      "name": "[ก่อนถูกโจมตี]"
    },
    {
      "id": "OnDirectAttack",
      "name": "[เมื่อโจมตีฝ่ายเดียว]"
    },
    {
      "id": "ReUseOnSucceedAttack",
      "name": "[ใช้อีกครั้ง - เมื่อโจมตี]"
    }
  ]
}