{
  "dataList": [
    {
      "id": 9013601,
      "levelList": [
        {
          "level": 1,
          "name": "<line-height=120%>...คกกระบาล\u200B</line-height>",
          "desc": "<line-height=130%>[WhenUse] หากเป้าหมายมี 5+ [Sinking], มอบ 1 [AttackDown]\u200B</line-height>",
          "coinlist": [
            {
              "coindescs": [
                {
                  "desc": "<line-height=130%>[OnSucceedAttack] มอบ 4 [Sinking]\u200B</line-height>"
                },
                {
                  "desc": "<line-height=130%>[OnSucceedAttack] มอบ 1 [Binding] ในเทิร์นหน้า\u200B</line-height>"
                }
              ]
            },
            {
              "coindescs": [
                {
                  "desc": "<line-height=130%>[OnSucceedAttack] มอบ 4 [Sinking]\u200B</line-height>"
                },
                {
                  "desc": "<line-height=130%>[OnSucceedAttack] มอบ 1 [Paralysis] ในเทิร์นหน้า\u200B</line-height>"
                }
              ]
            }
          ]
        }
      ]
    },
    {
      "id": 9013602,
      "levelList": [
        {
          "level": 1,
          "name": "<line-height=120%>...ให้สะอาด\u200B</line-height>",
          "desc": "<line-height=130%>[WhenUse] หากเป้าหมายมีค่าสติ 10 หรือต่ำกว่า, มอบ 2 [AttackDown]\n[WinDuel] มอบ 1 [Vulnerable]\u200B</line-height>",
          "coinlist": [
            {
              "coindescs": [
                {
                  "desc": "<line-height=130%>[OnSucceedAttack] มอบ 1 [PlusCoinValueDown] ในเทิร์นหน้า\u200B</line-height>"
                }
              ]
            },
            {
              "coindescs": [
                {
                  "desc": "<line-height=130%>[OnSucceedAttack] มอบ [Sinking] +3 ขั้น\u200B</line-height>"
                },
                {
                  "desc": "<line-height=130%>[OnSucceedAttack] มอบ 2 [Vulnerable] ในเทิร์นหน้า\u200B</line-height>"
                }
              ]
            }
          ]
        }
      ]
    },
    {
      "id": 9013603,
      "levelList": [
        {
          "level": 1,
          "name": "<line-height=120%>...ำสั่ง...!\u200B</line-height>",
          "desc": "<line-height=130%>[WhenUse] แต้มตั้งต้น +1 ต่อทุกๆ 3 [Sinking]บนเป้าหมาย (สูงสุด 3)\n[WinDuel] พันธมิตรทุกคน ฟื้นฟู 5 ค่าสติ\u200B</line-height>",
          "coinlist": [
            {
              "coindescs": [
                {
                  "desc": "<line-height=130%>[OnSucceedAttack] มอบ 8 [Sinking]\u200B</line-height>"
                },
                {
                  "desc": "<line-height=130%>[OnSucceedAttackHead] มอบ [Sinking] +2 ขั้น\u200B</line-height>"
                }
              ]
            },
            {
              "coindescs": [
                {
                  "desc": "<line-height=130%>[OnSucceedAttack] มอบ 8 [Sinking]\u200B</line-height>"
                },
                {
                  "desc": "<line-height=130%>[OnSucceedAttackHead] มอบ [Sinking] +2 ขั้น\u200B</line-height>"
                }
              ]
            },
            {
              "coindescs": [
                {
                  "desc": "<line-height=130%>[OnSucceedAttack] มอบ 8 [Sinking]\u200B</line-height>"
                },
                {
                  "desc": "<line-height=130%>[OnSucceedAttackHead] มอบ [Sinking] +2 ขั้น\u200B</line-height>"
                }
              ]
            }
          ]
        }
      ]
    },
    {
      "id": 9013604,
      "levelList": [
        {
          "level": 1,
          "name": "<line-height=120%>...เศษฝุ่น\u200B</line-height>",
          "desc": "<line-height=130%>[WhenUse] แต้มตั้งต้น +1 ต่อทุกๆ 6 [Sinking]บนเป้าหมาย (สูงสุด 3)\n[WhenUse] ทำ ความเสียหายเพิ่มเติม +10%  ต่อทุกๆ 6 ขั้น [Sinking]บนเป้าหมาย (สูงสุด 30%)\u200B</line-height>",
          "coinlist": [
            {
              "coindescs": [
                {
                  "desc": "<line-height=130%>[OnSucceedAttack] มอบ Gloom Affinityความเสียหายเพิ่มเติ่มเท่ากับ [Sinking]บนเป้าหมาย. ลดขั้น [Sinking] ที่เป้าหมายมี ไป 1\u200B</line-height>"
                }
              ]
            },
            {
              "coindescs": [
                {
                  "desc": "<line-height=130%>[OnSucceedAttack] มอบ Gloom Affinityความเสียหายเพิ่มเติ่มเท่ากับ [Sinking]บนเป้าหมาย. ลดขั้น [Sinking] ที่เป้าหมายมี ไป 1\u200B</line-height>"
                }
              ]
            },
            {
              "coindescs": [
                {
                  "desc": "<line-height=130%>[OnSucceedAttack] มอบ Gloom Affinityความเสียหายเพิ่มเติ่มเท่ากับ [Sinking]บนเป้าหมาย.\u200B</line-height>"
                },
                {
                  "desc": "<line-height=130%>[OnSucceedAttack] มอบ 4 [Sinking]\u200B</line-height>"
                },
                {
                  "desc": "<line-height=130%>[OnSucceedAttack] หากเป้าหมายมี 3+ ขั้น [Sinking], ใช้เหรียญนี้อีกครั้ง (2 ครั้ง)\u200B</line-height>"
                }
              ]
            }
          ]
        }
      ]
    },
    {
      "id": 9013605,
      "levelList": [
        {
          "level": 1,
          "name": "<line-height=120%>ไอ้ห...\u200B</line-height>",
          "desc": "<line-height=130%>ถ้ายูนิทนี้มี HP โล่ เหลือตอนจบเทิร์น, ลดขีด Stagger ไป 50\u200B</line-height>",
          "coinlist": [
            {}
          ]
        }
      ]
    },
    {
      "id": 9013701,
      "levelList": [
        {
          "level": 1,
          "name": "<line-height=120%>ไอ้เศ...\u200B</line-height>",
          "desc": "",
          "coinlist": [
            {
              "coindescs": [
                {
                  "desc": "<line-height=130%>[OnSucceedAttack] ได้รับ 1 [AttackUp] ในเทิร์นหน้า\u200B</line-height>"
                }
              ]
            },
            {
              "coindescs": [
                {
                  "desc": "<line-height=130%>[OnSucceedAttack] ได้รับ 1 [AttackUp] ในเทิร์นหน้า\u200B</line-height>"
                }
              ]
            }
          ]
        }
      ]
    },
    {
      "id": 9013702,
      "levelList": [
        {
          "level": 1,
          "name": "<line-height=120%>ฉันจะกำจ...\u200B</line-height>",
          "desc": "<line-height=130%>[WinDuel] แต้มตั้งต้น +1\u200B</line-height>",
          "coinlist": [
            {
              "coindescs": [
                {
                  "desc": "<line-height=130%>[OnSucceedAttack] หากเป้าหมายมี [AttackDown], ทำ 20% ของความเสียหายที่ทำไปเป็น ความเสียหายเพิ่มเติมทุบ\u200B</line-height>"
                }
              ]
            },
            {
              "coindescs": [
                {
                  "desc": "<line-height=130%>[OnSucceedAttack] หากเป้าหมายมี [AttackDown], ทำ 20% ของความเสียหายที่ทำไปเป็น ความเสียหายเพิ่มเติมทุบ\u200B</line-height>"
                }
              ]
            }
          ]
        }
      ]
    },
    {
      "id": 9013703,
      "levelList": [
        {
          "level": 1,
          "name": "<line-height=120%>เพื่อที่จะแก้...\u200B</line-height>",
          "desc": "<line-height=130%>[WinDuel] หากเป้าหมายมี 2+ [AttackDown], แต้มตั้งต้น +1\n[WhenUse] หากเป้าหมายมี [DefenseDown], ทำ 30% ของความเสียหายที่ทำไปเป็น ความเสียหายเพิ่มเติมทุบ\u200B</line-height>",
          "coinlist": [
            {},
            {
              "coindescs": [
                {
                  "desc": "<line-height=130%>[OnSucceedAttack] ฟื้นฟู 4 ค่าสติ แก่ตัวเอง\u200B</line-height>"
                }
              ]
            },
            {
              "coindescs": [
                {
                  "desc": "<line-height=130%>[OnSucceedAttack] ฟื้นฟู 4 ค่าสติ แก่ตัวเอง\u200B</line-height>"
                }
              ]
            },
            {
              "coindescs": [
                {
                  "desc": "<line-height=130%>[OnSucceedAttack] ฟื้นฟู 4 ค่าสติ แก่ตัวเอง\u200B</line-height>"
                }
              ]
            }
          ]
        }
      ]
    },
    {
      "id": 9013704,
      "levelList": [
        {
          "level": 1,
          "name": "<line-height=120%>... จัด แก\u200B</line-height>",
          "desc": "<line-height=130%>เล็งเป้าเป็นพิเศษหากเป้าหมายมี ผลด้านลบมากที่สุด\n[WinDuel] แต้มเหรียญ +1 ต่อทุกๆ 3 [DefenseDown] ที่เป้าหมายมี (สูงสุด 3)\u200B</line-height>",
          "coinlist": [
            {
              "coindescs": [
                {
                  "desc": "<line-height=130%>[OnSucceedAttack] มอบ 1 [Vulnerable]\u200B</line-height>"
                },
                {
                  "desc": "<line-height=130%>[OnSucceedAttack] มอบ 1 [Vulnerable] ในเทิร์นหน้า\u200B</line-height>"
                },
                {
                  "desc": "<line-height=130%>[OnSucceedAttack] มอบ 2 [Paralysis] ในเทิร์นหน้า\u200B</line-height>"
                }
              ]
            },
            {
              "coindescs": [
                {
                  "desc": "<line-height=130%>[OnSucceedAttack] ทำ ความเสียหายเพิ่มเติม +30%  ต่อทุกๆ 2 [AttackDown] ที่เป้าหมายมี (สูงสุด 120%)\u200B</line-height>"
                },
                {
                  "desc": "<line-height=130%>[OnSucceedAttackHead] หากเป้าหมายมี 3+ ผลด้านลบ ใช้เหรียญนี้อีกครั้ง (ครั้งเดียว)\u200B</line-height>"
                }
              ]
            }
          ]
        }
      ]
    },
    {
      "id": 9013705,
      "levelList": [
        {
          "level": 1,
          "name": "<line-height=120%>ป้องกัน\u200B</line-height>",
          "desc": "<line-height=130%>[StartBattle] ได้รับ 20 HP โล่ เพิ่มเติม ต่อพันธมิตรทุกๆคนที่อยู่ในสนาม\u200B</line-height>",
          "coinlist": [
            {
              "coindescs": [
                {
                  "desc": ""
                }
              ]
            }
          ]
        }
      ]
    },
    {
      "id": 9013801,
      "levelList": [
        {
          "level": 1,
          "name": "<line-height=120%>มาร์...\u200B</line-height>",
          "desc": "",
          "coinlist": [
            {
              "coindescs": [
                {
                  "desc": "<line-height=130%>[OnSucceedAttack] มอบ 2 [DefenseDown] ในเทิร์นหน้า\u200B</line-height>"
                }
              ]
            }
          ]
        }
      ]
    },
    {
      "id": 9013802,
      "levelList": [
        {
          "level": 1,
          "name": "<line-height=120%>...เต้\u200B</line-height>",
          "desc": "<line-height=130%>[WhenUse] หากเป้าหมายมี 2+ ผลด้านลบ แต้มตั้งต้น +1\u200B</line-height>",
          "coinlist": [
            {
              "coindescs": [
                {
                  "desc": "<line-height=130%>[OnSucceedAttack] มอบ 3 [DefenseDown] ในเทิร์นหน้า\u200B</line-height>"
                }
              ]
            }
          ]
        }
      ]
    },
    {
      "id": 9013803,
      "levelList": [
        {
          "level": 1,
          "name": "<line-height=120%>เฟ...ชห์\u200B</line-height>",
          "desc": "<line-height=130%>[WhenUse] หากเป้าหมายมี 4+ ผลด้านลบ แต้มเหรียญ +1\u200B</line-height>",
          "coinlist": [
            {
              "coindescs": [
                {
                  "desc": "<line-height=130%>[OnSucceedAttack] มอบ 1 [Binding] ในเทิร์นหน้า\u200B</line-height>"
                },
                {
                  "desc": "<line-height=130%>[OnSucceedAttack] มอบ 1 [PenetrateTakeDamageUp] ในเทิร์นหน้า\u200B</line-height>"
                }
              ]
            },
            {
              "coindescs": [
                {
                  "desc": "<line-height=130%>[OnSucceedAttack] มอบ 2 [Binding] ในเทิร์นหน้า\u200B</line-height>"
                }
              ]
            }
          ]
        }
      ]
    },
    {
      "id": 9013804,
      "levelList": [
        {
          "level": 1,
          "name": "<line-height=120%>คอร์...อท์\u200B</line-height>",
          "desc": "<line-height=130%>[WhenUse] หากเป้าหมายมี 5+ ผลด้านลบ แต้มตั้งต้น +2\n[WhenUse] หากเป้าหมายมี 5+ ผลด้านลบ ทำ +30% ความเสียหายเพิ่มเติ่ม\u200B</line-height>",
          "coinlist": [
            {
              "coindescs": [
                {
                  "desc": "<line-height=130%>[OnSucceedAttack] มอบ 2 [Vulnerable]\u200B</line-height>"
                }
              ]
            },
            {
              "coindescs": [
                {
                  "desc": "<line-height=130%>[OnSucceedAttack] มอบ 2 [Vulnerable] ในเทิร์นหน้า\u200B</line-height>"
                },
                {
                  "desc": "<line-height=130%>[OnSucceedAttack] หากเป้าหมายมี 5+ ผลด้านลบ ใช้เหรียญนี้อีกครั้ง (สูงสด 2 ครั้ง)\u200B</line-height>"
                },
                {
                  "desc": "<line-height=130%>[OnSucceedAttack] ลบ 1 ผลด้านลบแบบสุ่ม บนตัวเป้าหมายที่สามารถลบได้\u200B</line-height>"
                }
              ]
            }
          ]
        }
      ]
    },
    {
      "id": 9013805,
      "levelList": [
        {
          "level": 1,
          "name": "<line-height=120%>...\u200B</line-height>",
          "desc": "<line-height=130%>[OnSucceedEvade] ฟื้นฟู 5 ค่าสติ (สูงสด 2 ครั้ง)\u200B</line-height>",
          "coinlist": [
            {
              "coindescs": [
                {
                  "desc": ""
                }
              ]
            }
          ]
        }
      ]
    }
  ]
}